LICENSE.txt
MANIFEST.in
setup.cfg
setup.py
Pyll.egg-info/PKG-INFO
Pyll.egg-info/SOURCES.txt
Pyll.egg-info/dependency_links.txt
Pyll.egg-info/entry_points.txt
Pyll.egg-info/not-zip-safe
Pyll.egg-info/requires.txt
Pyll.egg-info/top_level.txt
pyll/__init__.py
pyll/application.py
pyll/configuration.py
pyll/decorators.py
pyll/middleware.py
pyll/router.py
pyll/tmplt.py
pyll/util.py
pyll/templates/MANIFEST.in
pyll/templates/__init__.py
pyll/templates/development.ini_tmpl
pyll/templates/setup.cfg_tmpl
pyll/templates/setup.py_tmpl
pyll/templates/+package+/__init__.py
pyll/templates/+package+/application/__init__.py_tmpl
pyll/templates/+package+/application/configuration.py_tmpl
pyll/templates/+package+/application/route_map.py_tmpl
pyll/templates/+package+/controllers/__init__.py
pyll/templates/+package+/controllers/api.py_tmpl
pyll/templates/+package+/controllers/auth.py_tmpl
pyll/templates/+package+/controllers/base.py_tmpl
pyll/templates/+package+/controllers/root.py_tmpl
pyll/templates/+package+/lib/__init__.py
pyll/templates/+package+/lib/app_globals.py_tmpl
pyll/templates/+package+/lib/forms.py_tmpl
pyll/templates/+package+/lib/helpers.py
pyll/templates/+package+/model/__init__.py_tmpl
pyll/templates/+package+/model/base.py_tmpl
pyll/templates/+package+/model/core.py_tmpl
pyll/templates/+package+/model/mapping.py_tmpl
pyll/templates/+package+/model/util.py_tmpl
pyll/templates/+package+/static/test.html_tmpl
pyll/templates/+package+/static/css/bootstrap-responsive.css
pyll/templates/+package+/static/css/bootstrap-responsive.min.css
pyll/templates/+package+/static/css/bootstrap.css
pyll/templates/+package+/static/css/bootstrap.min.css
pyll/templates/+package+/static/css/ellipsis-xbl.xml
pyll/templates/+package+/static/css/glyphicons.css
pyll/templates/+package+/static/css/style.css
pyll/templates/+package+/static/css/ui.jqgrid.css
pyll/templates/+package+/static/css/start/jquery-ui-1.9.2.custom.css
pyll/templates/+package+/static/css/start/jquery-ui-1.9.2.custom.min.css
pyll/templates/+package+/static/css/start/images/ui-bg_flat_55_999999_40x100.png
pyll/templates/+package+/static/css/start/images/ui-bg_flat_75_aaaaaa_40x100.png
