Metadata-Version: 1.0
Name: Pyll
Version: 0.4.3
Summary: An MVC architecture web framework.
Home-page: http://www.pyll.org
Author: Noel Morgan
Author-email: noel@pyll.org
License: MPL 2.0
Keywords: web framework sqlalchemy
Platform: UNKNOWN
Classifier: Environment :: Web Environment
